botframework/streaming/__init__.py
botframework/streaming/about.py
botframework/streaming/payload_stream.py
botframework/streaming/protocol_adapter.py
botframework/streaming/receive_request.py
botframework/streaming/receive_response.py
botframework/streaming/request_handler.py
botframework/streaming/streaming_request.py
botframework/streaming/streaming_response.py
botframework/streaming/payload_transport/__init__.py
botframework/streaming/payload_transport/payload_receiver.py
botframework/streaming/payload_transport/payload_sender.py
botframework/streaming/payload_transport/send_packet.py
botframework/streaming/payload_transport/send_queue.py
botframework/streaming/payloads/__init__.py
botframework/streaming/payloads/content_stream.py
botframework/streaming/payloads/header_serializer.py
botframework/streaming/payloads/payload_assembler_manager.py
botframework/streaming/payloads/request_manager.py
botframework/streaming/payloads/response_message_stream.py
botframework/streaming/payloads/send_operations.py
botframework/streaming/payloads/stream_manager.py
botframework/streaming/payloads/assemblers/__init__.py
botframework/streaming/payloads/assemblers/assembler.py
botframework/streaming/payloads/assemblers/payload_stream_assembler.py
botframework/streaming/payloads/assemblers/receive_request_assembler.py
botframework/streaming/payloads/assemblers/receive_response_assembler.py
botframework/streaming/payloads/disassemblers/__init__.py
botframework/streaming/payloads/disassemblers/cancel_disassembler.py
botframework/streaming/payloads/disassemblers/payload_disassembler.py
botframework/streaming/payloads/disassemblers/request_disassembler.py
botframework/streaming/payloads/disassemblers/response_disassembler.py
botframework/streaming/payloads/disassemblers/response_message_stream_disassembler.py
botframework/streaming/payloads/models/__init__.py
botframework/streaming/payloads/models/header.py
botframework/streaming/payloads/models/payload_types.py
botframework_streaming-4.15.1.dist-info/METADATA
botframework_streaming-4.15.1.dist-info/WHEEL
botframework_streaming-4.15.1.dist-info/top_level.txt
botframework_streaming-4.15.1.dist-info/RECORD
